MANIFEST.in
README.md
setup.py
streamlit_molecule_selection/__init__.py
streamlit_molecule_selection.egg-info/PKG-INFO
streamlit_molecule_selection.egg-info/SOURCES.txt
streamlit_molecule_selection.egg-info/dependency_links.txt
streamlit_molecule_selection.egg-info/requires.txt
streamlit_molecule_selection.egg-info/top_level.txt
streamlit_molecule_selection/frontend/build/asset-manifest.json
streamlit_molecule_selection/frontend/build/fee7cee.js
streamlit_molecule_selection/frontend/build/index.html
streamlit_molecule_selection/frontend/build/static/js/2.e5b824e2.chunk.js
streamlit_molecule_selection/frontend/build/static/js/2.e5b824e2.chunk.js.LICENSE.txt
streamlit_molecule_selection/frontend/build/static/js/2.e5b824e2.chunk.js.map
streamlit_molecule_selection/frontend/build/static/js/main.3292f3e4.chunk.js
streamlit_molecule_selection/frontend/build/static/js/main.3292f3e4.chunk.js.map
streamlit_molecule_selection/frontend/build/static/js/runtime-main.1a3f7aa5.js
streamlit_molecule_selection/frontend/build/static/js/runtime-main.1a3f7aa5.js.map